xdgmm/__init__.py
xdgmm/tests/test_XDGMM.py
xdgmm/xdgmm.py
tcup/__init__.py
tcup/numpyro.py
tcup/preprocess.py
tcup/priors.py
tcup/scale.py
tcup/stan/__init__.py
tcup/stan/model.py
tcup/stan/src/__init__.py
tcup/stan/src/ncup.stan
tcup/stan/src/tcup.stan
tcup/stan/src/template.stan
tcup/utils.py
tcup-0.7.1.dist-info/LICENSE
tcup-0.7.1.dist-info/WHEEL
tcup-0.7.1.dist-info/METADATA
tcup-0.7.1.dist-info/RECORD
